visl3d/__init__.py
visl3d/misc.py
visl3d/visual.py
visl3d/writers.py
visl3d/x3dom/js-colormaps.js
visl3d/x3dom/markers.js
visl3d/x3dom/x3dom.css
visl3d/x3dom/x3dom.js
visl3d-0.5.dist-info/METADATA
visl3d-0.5.dist-info/WHEEL
visl3d-0.5.dist-info/licenses/LICENSE
visl3d-0.5.dist-info/RECORD
