Metadata-Version: 2.4
Name: visl3d
Version: 0.5
Summary: Python library to create interactive 3D visualisations of astrophysical spectral line data
Project-URL: Repository, https://github.com/ixakalabadie/ViSL3D
Project-URL: Issues, https://github.com/ixakalabadie/ViSL3D/issues
Author-email: Ixaka Labadie García <ixaka.lab@gmail.com>
Maintainer-email: Ixaka Labadie García <ixaka.lab@gmail.com>
License: GNU GENERAL PUBLIC LICENSE
License-File: LICENSE
Keywords: 3d,astrophysics,datacube,interactive,spectral lines,visualisation
Classifier: Intended Audience :: Science/Research
Classifier: License :: OSI Approved :: GNU Lesser General Public License v3 (LGPLv3)
Classifier: Operating System :: OS Independent
Classifier: Programming Language :: Python :: 3
Classifier: Topic :: Scientific/Engineering :: Astronomy
Classifier: Topic :: Scientific/Engineering :: Visualization
Requires-Python: >=3.7
Requires-Dist: astropy
Requires-Dist: astroquery>=0.4.7
Requires-Dist: matplotlib
Requires-Dist: numpy
Requires-Dist: scikit-image
Requires-Dist: scipy
